[
	{
		"__TYPE__": "SharedSliceContent",
		"variation": "default",
		"primary": {
			"heading": {
				"__TYPE__": "StructuredTextContent",
				"value": [
					{
						"type": "heading1",
						"content": {
							"text": "Century"
						}
					}
				]
			},
			"body": {
				"__TYPE__": "StructuredTextContent",
				"value": [
					{
						"type": "paragraph",
						"content": {
							"text": "Dolor adipisicing consequat et ea aliqua deserunt. Magna irure nisi non fugiat quis deserunt excepteur ea pariatur nostrud magna minim."
						}
					}
				]
			},
			"button": {
				"__TYPE__": "LinkContent",
				"key": "bae9dd7c-17eb-498b-971e-74e9bb4aa7f5",
				"value": {
					"__TYPE__": "ExternalLink",
					"url": "https://prismic.io",
					"text": "completely"
				}
			}
		},
		"items": []
	}
]