[
	{
		"__TYPE__": "SharedSliceContent",
		"variation": "default_with_features_image",
		"primary": {
			"eyebrow": {
				"__TYPE__": "StructuredTextContent",
				"value": [
					{
						"type": "heading3",
						"content": {
							"text": "Telephone"
						}
					}
				]
			},
			"main_title": {
				"__TYPE__": "StructuredTextContent",
				"value": [
					{
						"type": "heading1",
						"content": {
							"text": "Folks"
						}
					}
				]
			},
			"subtitle": {
				"__TYPE__": "StructuredTextContent",
				"value": [
					{
						"type": "paragraph",
						"content": {
							"text": "Mollit sunt nulla magna anim excepteur dolor sint occaecat adipisicing aute fugiat id nisi elit."
						}
					}
				]
			},
			"summary_title": {
				"__TYPE__": "StructuredTextContent",
				"value": [
					{
						"type": "heading2",
						"content": {
							"text": "Field"
						}
					}
				]
			},
			"summary_text": {
				"__TYPE__": "StructuredTextContent",
				"value": [
					{
						"type": "paragraph",
						"content": {
							"text": "Do voluptate ea deserunt laborum reprehenderit. In exercitation exercitation sunt adipisicing."
						}
					}
				]
			},
			"primary_button": {
				"__TYPE__": "LinkContent",
				"key": "c464d39b-ebc6-46c0-9795-749bbe977e62",
				"value": {
					"__TYPE__": "ExternalLink",
					"url": "https://slicemachine.dev",
					"text": "outside"
				}
			},
			"features": {
				"__TYPE__": "GroupContentType",
				"value": [
					{
						"__TYPE__": "GroupItemContent",
						"value": [
							[
								"icon",
								{
									"__TYPE__": "ImageContent",
									"origin": {
										"id": "main",
										"url": "https://images.unsplash.com/photo-1560457079-9a6532ccb118",
										"width": 4160,
										"height": 3120
									},
									"url": "https://images.unsplash.com/photo-1560457079-9a6532ccb118",
									"width": 4160,
									"height": 3120,
									"edit": {
										"zoom": 1,
										"crop": {
											"x": 0,
											"y": 0
										},
										"background": "transparent"
									},
									"alt": "solid"
								}
							],
							[
								"text",
								{
									"__TYPE__": "FieldContent",
									"value": "ask",
									"type": "Text"
								}
							]
						]
					}
				]
			},
			"preview_image": {
				"__TYPE__": "ImageContent",
				"origin": {
					"id": "main",
					"url": "https://images.unsplash.com/photo-1600804931749-2da4ce26c869",
					"width": 3199,
					"height": 3199
				},
				"url": "https://images.unsplash.com/photo-1600804931749-2da4ce26c869",
				"width": 3199,
				"height": 3199,
				"edit": {
					"zoom": 1,
					"crop": {
						"x": 0,
						"y": 0
					},
					"background": "transparent"
				},
				"alt": "swam"
			}
		},
		"items": []
	}
]